README.rst
setup.py
penkit/__init__.py
penkit/mpl_preview.py
penkit/plot.py
penkit/preview.py
penkit/projection.py
penkit/shapes.py
penkit/surfaces.py
penkit/turtle.py
penkit/write.py
penkit.egg-info/PKG-INFO
penkit.egg-info/SOURCES.txt
penkit.egg-info/dependency_links.txt
penkit.egg-info/top_level.txt
penkit/fractal/__init__.py
penkit/fractal/l_systems.py
penkit/textures/__init__.py
penkit/textures/util.py