Metadata-Version: 1.0
Name: penkit
Version: 0.0.6
Summary: Library for pen plotting in Python.
Home-page: https://github.com/paulgb/penkit
Author: Paul Butler
Author-email: penkit@paulbutler.org
License: UNKNOWN
Platform: UNKNOWN
